pybloom/__init__.py
pybloom/benchmarks.py
pybloom/pybloom.py
pybloom/tests.py
pybloom/utils.py
pybloom3_richard-0.0.1.dist-info/LICENSE.txt
pybloom3_richard-0.0.1.dist-info/METADATA
pybloom3_richard-0.0.1.dist-info/WHEEL
pybloom3_richard-0.0.1.dist-info/top_level.txt
pybloom3_richard-0.0.1.dist-info/zip-safe
pybloom3_richard-0.0.1.dist-info/RECORD
